retail_order_utils/__init__.py
retail_order_utils/core.py
retail_order_utils-0.0.1.dist-info/licenses/LICENSE
retail_order_utils-0.0.1.dist-info/METADATA
retail_order_utils-0.0.1.dist-info/WHEEL
retail_order_utils-0.0.1.dist-info/top_level.txt
retail_order_utils-0.0.1.dist-info/RECORD
