Metadata-Version: 2.4
Name: retail_order_utils
Version: 0.0.1
Summary: Library for retail order IDs, tracking and delivery estimation.
Author-email: kishorekanna <Knnkshr@gmail.com>
License: MIT
Project-URL: Homepage, https://example.com
Classifier: Programming Language :: Python :: 3
Classifier: License :: OSI Approved :: MIT License
Classifier: Intended Audience :: Developers
Classifier: Topic :: Software Development :: Libraries
Requires-Python: >=3.10
License-File: LICENSE
Dynamic: license-file
